pangea_client/__init__.py
pangea_client/client.py
pangea_client/types.py
pangea_client-0.3.12.dist-info/METADATA
pangea_client-0.3.12.dist-info/WHEEL
pangea_client-0.3.12.dist-info/RECORD
