Metadata-Version: 2.1
Name: pangea-client
Version: 0.3.12
Summary: Pangea Client connects you to The First Immersive Web3 Environment
Home-page: https://pangea.foundation
License: MIT
Keywords: pangea,blockchain,crypto,data,datasci,dsci,ethereum,bitcoin,wallet,pandas,polars,datafusion,duckdb,sql,rpc,web3,ethers
Author: Pangea Foundation
Author-email: info@pangea.foundation
Requires-Python: >=3.10
Classifier: License :: OSI Approved :: MIT License
Classifier: Programming Language :: Python :: 3
Classifier: Programming Language :: Python :: 3.10
Classifier: Programming Language :: Python :: 3.11
Classifier: Programming Language :: Python :: 3.12
Classifier: Programming Language :: Python :: 3.13
Requires-Dist: websockets (==11.0.3)
Project-URL: Documentation, https://docs.pangea.foundation/introduction.html
Project-URL: Repository, https://github.com/PangeaFoundation/pangea-client
